tests/__init__.py
tests/test_decorator.py
tests/test_encoder.py
tests/test_formatter.py
tests/test_logger.py
tests/test_printable.py
vulcan_logger/__init__.py
vulcan_logger/decorator.py
vulcan_logger/encoder.py
vulcan_logger/formatter.py
vulcan_logger/logger.py
vulcan_logger/printable.py
vulcan_logger-1.10.0.dist-info/LICENSE
vulcan_logger-1.10.0.dist-info/METADATA
vulcan_logger-1.10.0.dist-info/WHEEL
vulcan_logger-1.10.0.dist-info/top_level.txt
vulcan_logger-1.10.0.dist-info/RECORD
