Metadata-Version: 2.1
Name: vulcan-logger
Version: 1.10.0
Summary: A logging utility package with colored logs.
License-File: LICENSE
Requires-Dist: coloredlogs
